<?xml version='1.0' encoding='utf-8'?>
<TLote_GNRE xmlns="http://www.gnre.pe.gov.br" versao="2.00"><guias><TDadosGNRE versao="2.00"><ufFavorecida>RJ</ufFavorecida><tipoGnre>0</tipoGnre><contribuinteEmitente><identificacao><CNPJ>06885798000182</CNPJ></identificacao><razaoSocial>SANTO GRAO COMERCIAL IMPORT E EXPORT DE PROD ALIMENT LTDA</razaoSocial><endereco>R NELSON RAINERI</endereco><municipio>13009</municipio><uf>SP</uf><cep>06702155</cep></contribuinteEmitente><itensGNRE><item><receita>100099</receita><documentoOrigem tipo="24">35240306885798000182550010000349691617597492</documentoOrigem><produto>89</produto><dataVencimento>2024-05-17</dataVencimento><valor tipo="11">33.67</valor><valor tipo="12">4.46</valor><contribuinteDestinatario><identificacao><IE>77056548</IE></identificacao></contribuinteDestinatario><camposExtras><campoExtra><codigo>117</codigo><valor>2024-05-17</valor></campoExtra><campoExtra><codigo>118</codigo><valor>Loja 221</valor></campoExtra></camposExtras></item></itensGNRE><valorGNRE>38.13</valorGNRE><dataPagamento>2024-05-17</dataPagamento></TDadosGNRE><TDadosGNRE versao="2.00"><ufFavorecida>RJ</ufFavorecida><tipoGnre>0</tipoGnre><contribuinteEmitente><identificacao><CNPJ>06885798000182</CNPJ></identificacao><razaoSocial>SANTO GRAO COMERCIAL IMPORT E EXPORT DE PROD ALIMENT LTDA</razaoSocial><endereco>R NELSON RAINERI</endereco><municipio>13009</municipio><uf>SP</uf><cep>06702155</cep></contribuinteEmitente><itensGNRE><item><receita>100099</receita><documentoOrigem tipo="24">35240306885798000182550010000349531131808234</documentoOrigem><produto>89</produto><dataVencimento>2024-05-17</dataVencimento><valor tipo="11">113.61</valor><valor tipo="12">15.07</valor><contribuinteDestinatario><identificacao><IE>85222856</IE></identificacao></contribuinteDestinatario><camposExtras><campoExtra><codigo>117</codigo><valor>2024-05-17</valor></campoExtra><campoExtra><codigo>118</codigo><valor>Loja 108</valor></campoExtra></camposExtras></item></itensGNRE><valorGNRE>128.68</valorGNRE><dataPagamento>2024-05-17</dataPagamento></TDadosGNRE></guias></TLote_GNRE>